pysentel/__init__.py
pysentel/__main__.py
pysentel/helpers.py
pysentel/pysentel.py
pysentel-0.1b2.dist-info/LICENSE
pysentel-0.1b2.dist-info/METADATA
pysentel-0.1b2.dist-info/WHEEL
pysentel-0.1b2.dist-info/top_level.txt
pysentel-0.1b2.dist-info/RECORD
