Metadata-Version: 2.1
Name: pysentel
Version: 0.1b2
Summary: A python script for fetching 1-wire sensor-data and ingesting into InfluxDB.
Home-page: https://github.com/danniranderis/pysentel
Author: Danni Randeris
Author-email: danni@danniranderis.dk
Maintainer: Danni Randeris
Maintainer-email: danni@danniranderis.dk
License: MIT
Download-URL: https://github.com/danniranderis/pysentel
Keywords: 1-wire,ds18b20,influxdb
Platform: Linux
Classifier: Development Status :: 4 - Beta
Classifier: License :: OSI Approved :: MIT License
Classifier: Operating System :: POSIX :: Linux
Classifier: Programming Language :: Python :: 3
Classifier: Programming Language :: Python :: 3.7
Classifier: Programming Language :: Python :: 3.8
Classifier: Programming Language :: Python :: 3.9
Classifier: Topic :: Software Development :: Libraries :: Python Modules
Requires-Python: >=3.7
Requires-Dist: w1thermsensor (==2.0.0)
Requires-Dist: influxdb-client (==1.14.0)
